{
  "name": "first-time-value",
  "homepage": "https://www.hexstreamsoft.com/libraries/first-time-value/",
  "shortdesc": {
    "en": "Returns the result of evaluating a form in the current lexical and dynamic context the first time it's encountered, and the cached result of that computation on subsequent evaluations."
  },
  "repository": {
    "browse": "https://github.com/Hexstream/first-time-value",
    "location": "https://github.com/Hexstream/first-time-value.git"
  },
  "license": "https://github.com/Hexstream/first-time-value/blob/master/UNLICENSE"
}
